[
{
  "directory": "D:/ZWH/Data Structure/Tree/build",
  "command": "\"D:\\Program Files\\mingw64\\bin\\g++.exe\"  @CMakeFiles/untitled.dir/includes_CXX.rsp -g -o CMakeFiles\\untitled.dir\\main.cpp.obj -c \"D:\\ZWH\\Data Structure\\Tree\\main.cpp\"",
  "file": "D:/ZWH/Data Structure/Tree/main.cpp"
},
{
  "directory": "D:/ZWH/Data Structure/Tree/build/Includes",
  "command": "\"D:\\Program Files\\mingw64\\bin\\g++.exe\"  @CMakeFiles/Includes.dir/includes_CXX.rsp -g -o CMakeFiles\\Includes.dir\\include.cpp.obj -c \"D:\\ZWH\\Data Structure\\Tree\\Includes\\include.cpp\"",
  "file": "D:/ZWH/Data Structure/Tree/Includes/include.cpp"
},
{
  "directory": "D:/ZWH/Data Structure/Tree/build/Libraries/ZWH_App",
  "command": "\"D:\\Program Files\\mingw64\\bin\\g++.exe\"  @CMakeFiles/ZWH_App.dir/includes_CXX.rsp -g -o CMakeFiles\\ZWH_App.dir\\string_zwh.cpp.obj -c \"D:\\ZWH\\Data Structure\\Tree\\Libraries\\ZWH_App\\string_zwh.cpp\"",
  "file": "D:/ZWH/Data Structure/Tree/Libraries/ZWH_App/string_zwh.cpp"
},
{
  "directory": "D:/ZWH/Data Structure/Tree/build/Libraries/ZWH_App",
  "command": "\"D:\\Program Files\\mingw64\\bin\\g++.exe\"  @CMakeFiles/ZWH_App.dir/includes_CXX.rsp -g -o CMakeFiles\\ZWH_App.dir\\collection_zwh.cpp.obj -c \"D:\\ZWH\\Data Structure\\Tree\\Libraries\\ZWH_App\\collection_zwh.cpp\"",
  "file": "D:/ZWH/Data Structure/Tree/Libraries/ZWH_App/collection_zwh.cpp"
},
{
  "directory": "D:/ZWH/Data Structure/Tree/build/Libraries/ZWH_App",
  "command": "\"D:\\Program Files\\mingw64\\bin\\g++.exe\"  @CMakeFiles/ZWH_App.dir/includes_CXX.rsp -g -o \"CMakeFiles\\ZWH_App.dir\\Stacks&Queues.cpp.obj\" -c \"D:\\ZWH\\Data Structure\\Tree\\Libraries\\ZWH_App\\Stacks&Queues.cpp\"",
  "file": "D:/ZWH/Data Structure/Tree/Libraries/ZWH_App/Stacks&Queues.cpp"
},
{
  "directory": "D:/ZWH/Data Structure/Tree/build/Libraries/ZWH_Class",
  "command": "\"D:\\Program Files\\mingw64\\bin\\g++.exe\"  @CMakeFiles/ZWH_Class.dir/includes_CXX.rsp -g -o CMakeFiles\\ZWH_Class.dir\\RandomBag.cpp.obj -c \"D:\\ZWH\\Data Structure\\Tree\\Libraries\\ZWH_Class\\RandomBag.cpp\"",
  "file": "D:/ZWH/Data Structure/Tree/Libraries/ZWH_Class/RandomBag.cpp"
},
{
  "directory": "D:/ZWH/Data Structure/Tree/build/Libraries/ZWH_Class",
  "command": "\"D:\\Program Files\\mingw64\\bin\\g++.exe\"  @CMakeFiles/ZWH_Class.dir/includes_CXX.rsp -g -o CMakeFiles\\ZWH_Class.dir\\BankAccount.cpp.obj -c \"D:\\ZWH\\Data Structure\\Tree\\Libraries\\ZWH_Class\\BankAccount.cpp\"",
  "file": "D:/ZWH/Data Structure/Tree/Libraries/ZWH_Class/BankAccount.cpp"
},
{
  "directory": "D:/ZWH/Data Structure/Tree/build/Libraries/ZWH_Class",
  "command": "\"D:\\Program Files\\mingw64\\bin\\g++.exe\"  @CMakeFiles/ZWH_Class.dir/includes_CXX.rsp -g -o CMakeFiles\\ZWH_Class.dir\\maze.cpp.obj -c \"D:\\ZWH\\Data Structure\\Tree\\Libraries\\ZWH_Class\\maze.cpp\"",
  "file": "D:/ZWH/Data Structure/Tree/Libraries/ZWH_Class/maze.cpp"
}
]